README.txt
setup.py
pyxid/__init__.py
pyxid/constants.py
pyxid/internal.py
pyxid/keymaps.py
pyxid/pyxid_impl.py
pyxid/serial_wrapper.py
pyxid.egg-info/PKG-INFO
pyxid.egg-info/SOURCES.txt
pyxid.egg-info/dependency_links.txt
pyxid.egg-info/requires.txt
pyxid.egg-info/top_level.txt