Metadata-Version: 1.0
Name: pyxid
Version: 1.0
Summary: Pure python library for communicating with Cedrus XID and StimTracker devices.
Home-page: http://www.github.com/cedrus-opensource/pyxid/
Author: Cedrus Corporation
Author-email: opensource@cedrus.com
License: BSD
Keywords: cedrus xid XID stimulus response data collection
Platform: UNKNOWN
Classifier: Development Status :: 4 - Beta
Classifier: Intended Audience :: Developers
Classifier: License :: OSI Approved :: BSD License
Classifier: Topic :: System :: Hardware
Classifier: Programming Language :: Python
Classifier: Operating System :: MacOS :: MacOS X
Classifier: Operating System :: Microsoft :: Windows
Classifier: Operating System :: POSIX
